[{"line_index_1":332.0,"heRef_2":"\u05de\u05e9\u05dc\u05d9 \u05d8\u05d6, \u05db\u05d7,","path_2":"..\\..\\refs\\\u05d0\u05d5\u05e6\u05e8\u05d9\u05d0\\\u05ea\u05e0\u05da\\\u05db\u05ea\u05d5\u05d1\u05d9\u05dd\\\u05de\u05e9\u05dc\u05d9","line_index_2":485.0,"Conection Type":null},{"line_index_1":339.0,"heRef_2":"\u05e0\u05d7\u05d5\u05dd \u05d2, \u05d0,","path_2":"..\\..\\refs\\\u05d0\u05d5\u05e6\u05e8\u05d9\u05d0\\\u05ea\u05e0\u05da\\\u05e0\u05d1\u05d9\u05d0\u05d9\u05dd\\\u05e0\u05d7\u05d5\u05dd","line_index_2":33.0,"Conection Type":null},{"line_index_1":41.0,"heRef_2":"\u05ea\u05d4\u05d9\u05dc\u05d9\u05dd \u05e0, \u05d1,","path_2":"..\\..\\refs\\\u05d0\u05d5\u05e6\u05e8\u05d9\u05d0\\\u05ea\u05e0\u05da\\\u05db\u05ea\u05d5\u05d1\u05d9\u05dd\\\u05ea\u05d4\u05d9\u05dc\u05d9\u05dd","line_index_2":810.0,"Conection Type":null},{"line_index_1":371.0,"heRef_2":"\u05de\u05e9\u05dc\u05d9 \u05d9\u05d2, \u05d8\u05d6,","path_2":"..\\..\\refs\\\u05d0\u05d5\u05e6\u05e8\u05d9\u05d0\\\u05ea\u05e0\u05da\\\u05db\u05ea\u05d5\u05d1\u05d9\u05dd\\\u05de\u05e9\u05dc\u05d9","line_index_2":377.0,"Conection Type":null},{"line_index_1":44.0,"heRef_2":"\u05e9\u05d9\u05e8 \u05d4\u05e9\u05d9\u05e8\u05d9\u05dd \u05d6, \u05d9\u05d1,","path_2":"..\\..\\refs\\\u05d0\u05d5\u05e6\u05e8\u05d9\u05d0\\\u05ea\u05e0\u05da\\\u05db\u05ea\u05d5\u05d1\u05d9\u05dd\\\u05e9\u05d9\u05e8 \u05d4\u05e9\u05d9\u05e8\u05d9\u05dd","line_index_2":109.0,"Conection Type":null},{"line_index_1":394.0,"heRef_2":"\u05de\u05e9\u05dc\u05d9 \u05db\u05d6, \u05d9\u05d8,","path_2":"..\\..\\refs\\\u05d0\u05d5\u05e6\u05e8\u05d9\u05d0\\\u05ea\u05e0\u05da\\\u05db\u05ea\u05d5\u05d1\u05d9\u05dd\\\u05de\u05e9\u05dc\u05d9","line_index_2":816.0,"Conection Type":"quotation"},{"line_index_1":14.0,"heRef_2":"\u05de\u05e9\u05dc\u05d9 \u05db\u05d4, \u05db\u05d4,","path_2":"..\\..\\refs\\\u05d0\u05d5\u05e6\u05e8\u05d9\u05d0\\\u05ea\u05e0\u05da\\\u05db\u05ea\u05d5\u05d1\u05d9\u05dd\\\u05de\u05e9\u05dc\u05d9","line_index_2":764.0,"Conection Type":null},{"line_index_1":117.0,"heRef_2":"\u05de\u05e9\u05dc\u05d9 \u05db\u05d3, \u05d3,","path_2":"..\\..\\refs\\\u05d0\u05d5\u05e6\u05e8\u05d9\u05d0\\\u05ea\u05e0\u05da\\\u05db\u05ea\u05d5\u05d1\u05d9\u05dd\\\u05de\u05e9\u05dc\u05d9","line_index_2":708.0,"Conection Type":null},{"line_index_1":148.0,"heRef_2":"\u05d5\u05d9\u05e7\u05e8\u05d0 \u05e8\u05d1\u05d4 \u05db\u05d2, \u05d8,","path_2":"..\\..\\refs\\\u05d0\u05d5\u05e6\u05e8\u05d9\u05d0\\\u05de\u05d3\u05e8\u05e9\\\u05d0\u05d2\u05d3\u05d4\\\u05de\u05d3\u05e8\u05e9 \u05e8\u05d1\u05d4\\\u05d5\u05d9\u05e7\u05e8\u05d0 \u05e8\u05d1\u05d4","line_index_2":215.0,"Conection Type":null},{"line_index_1":4.0,"heRef_2":"\u05de\u05e9\u05e0\u05d4 \u05d0\u05d1\u05d5\u05ea \u05d5, \u05d0,","path_2":"..\\..\\refs\\\u05d0\u05d5\u05e6\u05e8\u05d9\u05d0\\\u05de\u05e9\u05e0\u05d4\\\u05e1\u05d3\u05e8 \u05e0\u05d6\u05d9\u05e7\u05d9\u05df\\\u05de\u05e9\u05e0\u05d4 \u05d0\u05d1\u05d5\u05ea","line_index_2":105.0,"Conection Type":null},{"line_index_1":4.0,"heRef_2":"\u05ea\u05d4\u05d9\u05dc\u05d9\u05dd \u05e1\u05d0, \u05d4,","path_2":"..\\..\\refs\\\u05d0\u05d5\u05e6\u05e8\u05d9\u05d0\\\u05ea\u05e0\u05da\\\u05db\u05ea\u05d5\u05d1\u05d9\u05dd\\\u05ea\u05d4\u05d9\u05dc\u05d9\u05dd","line_index_2":989.0,"Conection Type":null},{"line_index_1":372.0,"heRef_2":"\u05e7\u05d4\u05dc\u05ea \u05d4, \u05d9,","path_2":"..\\..\\refs\\\u05d0\u05d5\u05e6\u05e8\u05d9\u05d0\\\u05ea\u05e0\u05da\\\u05db\u05ea\u05d5\u05d1\u05d9\u05dd\\\u05e7\u05d4\u05dc\u05ea","line_index_2":99.0,"Conection Type":null},{"line_index_1":25.0,"heRef_2":"\u05e7\u05d4\u05dc\u05ea \u05d8, \u05d9\u05d3,","path_2":"..\\..\\refs\\\u05d0\u05d5\u05e6\u05e8\u05d9\u05d0\\\u05ea\u05e0\u05da\\\u05db\u05ea\u05d5\u05d1\u05d9\u05dd\\\u05e7\u05d4\u05dc\u05ea","line_index_2":184.0,"Conection Type":null},{"line_index_1":394.0,"heRef_2":"\u05d4\u05d5\u05e9\u05e2 \u05d9\u05d0, \u05d0,","path_2":"..\\..\\refs\\\u05d0\u05d5\u05e6\u05e8\u05d9\u05d0\\\u05ea\u05e0\u05da\\\u05e0\u05d1\u05d9\u05d0\u05d9\u05dd\\\u05d4\u05d5\u05e9\u05e2","line_index_2":159.0,"Conection Type":"quotation"},{"line_index_1":100.0,"heRef_2":"\u05d4\u05d5\u05e9\u05e2 \u05d9\u05d1, \u05d0,","path_2":"..\\..\\refs\\\u05d0\u05d5\u05e6\u05e8\u05d9\u05d0\\\u05ea\u05e0\u05da\\\u05e0\u05d1\u05d9\u05d0\u05d9\u05dd\\\u05d4\u05d5\u05e9\u05e2","line_index_2":171.0,"Conection Type":null},{"line_index_1":296.0,"heRef_2":"\u05d9\u05e9\u05e2\u05d9\u05d4\u05d5 \u05de\u05d2, \u05d3,","path_2":"..\\..\\refs\\\u05d0\u05d5\u05e6\u05e8\u05d9\u05d0\\\u05ea\u05e0\u05da\\\u05e0\u05d1\u05d9\u05d0\u05d9\u05dd\\\u05d9\u05e9\u05e2\u05d9\u05d4\u05d5","line_index_2":899.0,"Conection Type":null},{"line_index_1":81.0,"heRef_2":"\u05d9\u05e9\u05e2\u05d9\u05d4\u05d5 \u05e0\u05d3, \u05d8\u05d5,","path_2":"..\\..\\refs\\\u05d0\u05d5\u05e6\u05e8\u05d9\u05d0\\\u05ea\u05e0\u05da\\\u05e0\u05d1\u05d9\u05d0\u05d9\u05dd\\\u05d9\u05e9\u05e2\u05d9\u05d4\u05d5","line_index_2":1139.0,"Conection Type":null},{"line_index_1":310.0,"heRef_2":"\u05d9\u05e8\u05de\u05d9\u05d4\u05d5 \u05d1, \u05dc\u05d5,","path_2":"..\\..\\refs\\\u05d0\u05d5\u05e6\u05e8\u05d9\u05d0\\\u05ea\u05e0\u05da\\\u05e0\u05d1\u05d9\u05d0\u05d9\u05dd\\\u05d9\u05e8\u05de\u05d9\u05d4\u05d5","line_index_2":58.0,"Conection Type":null},{"line_index_1":247.0,"heRef_2":"\u05d0\u05d9\u05d5\u05d1 \u05dc\u05d2, \u05dc\u05d2,","path_2":"..\\..\\refs\\\u05d0\u05d5\u05e6\u05e8\u05d9\u05d0\\\u05ea\u05e0\u05da\\\u05db\u05ea\u05d5\u05d1\u05d9\u05dd\\\u05d0\u05d9\u05d5\u05d1","line_index_2":848.0,"Conection Type":null},{"line_index_1":275.0,"heRef_2":"\u05d0\u05d9\u05d5\u05d1 \u05dc\u05d5, \u05d1,","path_2":"..\\..\\refs\\\u05d0\u05d5\u05e6\u05e8\u05d9\u05d0\\\u05ea\u05e0\u05da\\\u05db\u05ea\u05d5\u05d1\u05d9\u05dd\\\u05d0\u05d9\u05d5\u05d1","line_index_2":906.0,"Conection Type":null},{"line_index_1":364.0,"heRef_2":"\u05d9\u05d4\u05d5\u05e9\u05e2 \u05d8\u05d5, \u05d9\u05d8,","path_2":"..\\..\\refs\\\u05d0\u05d5\u05e6\u05e8\u05d9\u05d0\\\u05ea\u05e0\u05da\\\u05e0\u05d1\u05d9\u05d0\u05d9\u05dd\\\u05d9\u05d4\u05d5\u05e9\u05e2","line_index_2":386.0,"Conection Type":null},{"line_index_1":104.0,"heRef_2":"\u05db\u05ea\u05d5\u05d1\u05d5\u05ea \u05e7\u05d3., \u05d5,","path_2":"..\\..\\refs\\\u05d0\u05d5\u05e6\u05e8\u05d9\u05d0\\\u05ea\u05dc\u05de\u05d5\u05d3\\\u05d1\u05d1\u05dc\u05d9\\\u05e1\u05d3\u05e8 \u05e0\u05e9\u05d9\u05dd\\\u05db\u05ea\u05d5\u05d1\u05d5\u05ea","line_index_2":2949.0,"Conection Type":null}]