[{"line_index_1":198.0,"heRef_2":"\u05d9\u05d1\u05de\u05d5\u05ea \u05de\u05d7:, \u05d1,","path_2":"\u05d0\u05d5\u05e6\u05e8\u05d9\u05d0\\\u05ea\u05dc\u05de\u05d5\u05d3\\\u05d1\u05d1\u05dc\u05d9\\\u05e1\u05d3\u05e8 \u05e0\u05e9\u05d9\u05dd\\\u05d9\u05d1\u05de\u05d5\u05ea","line_index_2":1621.0,"Conection Type":null},{"line_index_1":225.0,"heRef_2":"\u05d9\u05d5\u05de\u05d0 \u05e0., \u05d7,","path_2":"\u05d0\u05d5\u05e6\u05e8\u05d9\u05d0\\\u05ea\u05dc\u05de\u05d5\u05d3\\\u05d1\u05d1\u05dc\u05d9\\\u05e1\u05d3\u05e8 \u05de\u05d5\u05e2\u05d3\\\u05d9\u05d5\u05de\u05d0","line_index_2":1279.0,"Conection Type":null},{"line_index_1":245.0,"heRef_2":"\u05d9\u05d1\u05de\u05d5\u05ea \u05e7\u05d0., \u05d8,","path_2":"\u05d0\u05d5\u05e6\u05e8\u05d9\u05d0\\\u05ea\u05dc\u05de\u05d5\u05d3\\\u05d1\u05d1\u05dc\u05d9\\\u05e1\u05d3\u05e8 \u05e0\u05e9\u05d9\u05dd\\\u05d9\u05d1\u05de\u05d5\u05ea","line_index_2":3349.0,"Conection Type":null},{"line_index_1":257.0,"heRef_2":"\u05d6\u05d1\u05d7\u05d9\u05dd \u05e0\u05d3:, \u05d6,","path_2":"\u05d0\u05d5\u05e6\u05e8\u05d9\u05d0\\\u05ea\u05dc\u05de\u05d5\u05d3\\\u05d1\u05d1\u05dc\u05d9\\\u05e1\u05d3\u05e8 \u05e7\u05d3\u05e9\u05d9\u05dd\\\u05d6\u05d1\u05d7\u05d9\u05dd","line_index_2":1888.0,"Conection Type":null},{"line_index_1":291.0,"heRef_2":"\u05d9\u05d1\u05de\u05d5\u05ea \u05dc\u05d5., \u05d2,","path_2":"\u05d0\u05d5\u05e6\u05e8\u05d9\u05d0\\\u05ea\u05dc\u05de\u05d5\u05d3\\\u05d1\u05d1\u05dc\u05d9\\\u05e1\u05d3\u05e8 \u05e0\u05e9\u05d9\u05dd\\\u05d9\u05d1\u05de\u05d5\u05ea","line_index_2":1104.0,"Conection Type":null},{"line_index_1":320.0,"heRef_2":"\u05d9\u05d1\u05de\u05d5\u05ea \u05e4\u05d2:, \u05d4,","path_2":"\u05d0\u05d5\u05e6\u05e8\u05d9\u05d0\\\u05ea\u05dc\u05de\u05d5\u05d3\\\u05d1\u05d1\u05dc\u05d9\\\u05e1\u05d3\u05e8 \u05e0\u05e9\u05d9\u05dd\\\u05d9\u05d1\u05de\u05d5\u05ea","line_index_2":2783.0,"Conection Type":null},{"line_index_1":10.0,"heRef_2":"\u05d9\u05d1\u05de\u05d5\u05ea \u05de\u05d5:, \u05d8\u05d6,","path_2":"\u05d0\u05d5\u05e6\u05e8\u05d9\u05d0\\\u05ea\u05dc\u05de\u05d5\u05d3\\\u05d1\u05d1\u05dc\u05d9\\\u05e1\u05d3\u05e8 \u05e0\u05e9\u05d9\u05dd\\\u05d9\u05d1\u05de\u05d5\u05ea","line_index_2":1568.0,"Conection Type":null},{"line_index_1":568.0,"heRef_2":"\u05d9\u05d1\u05de\u05d5\u05ea \u05d5:, \u05d8\u05d5,","path_2":"\u05d0\u05d5\u05e6\u05e8\u05d9\u05d0\\\u05ea\u05dc\u05de\u05d5\u05d3\\\u05d1\u05d1\u05dc\u05d9\\\u05e1\u05d3\u05e8 \u05e0\u05e9\u05d9\u05dd\\\u05d9\u05d1\u05de\u05d5\u05ea","line_index_2":137.0,"Conection Type":null},{"line_index_1":571.0,"heRef_2":"\u05d6\u05d1\u05d7\u05d9\u05dd \u05e7., \u05d4,","path_2":"\u05d0\u05d5\u05e6\u05e8\u05d9\u05d0\\\u05ea\u05dc\u05de\u05d5\u05d3\\\u05d1\u05d1\u05dc\u05d9\\\u05e1\u05d3\u05e8 \u05e7\u05d3\u05e9\u05d9\u05dd\\\u05d6\u05d1\u05d7\u05d9\u05dd","line_index_2":3259.0,"Conection Type":null},{"line_index_1":602.0,"heRef_2":"\u05d9\u05d1\u05de\u05d5\u05ea \u05e7\u05d0., \u05d8\u05d5,","path_2":"\u05d0\u05d5\u05e6\u05e8\u05d9\u05d0\\\u05ea\u05dc\u05de\u05d5\u05d3\\\u05d1\u05d1\u05dc\u05d9\\\u05e1\u05d3\u05e8 \u05e0\u05e9\u05d9\u05dd\\\u05d9\u05d1\u05de\u05d5\u05ea","line_index_2":3355.0,"Conection Type":null},{"line_index_1":682.0,"heRef_2":"\u05d6\u05d1\u05d7\u05d9\u05dd \u05e0., \u05d1,","path_2":"\u05d0\u05d5\u05e6\u05e8\u05d9\u05d0\\\u05ea\u05dc\u05de\u05d5\u05d3\\\u05d1\u05d1\u05dc\u05d9\\\u05e1\u05d3\u05e8 \u05e7\u05d3\u05e9\u05d9\u05dd\\\u05d6\u05d1\u05d7\u05d9\u05dd","line_index_2":1752.0,"Conection Type":null},{"line_index_1":720.0,"heRef_2":"\u05d6\u05d1\u05d7\u05d9\u05dd \u05e1., \u05d9\u05d2,","path_2":"\u05d0\u05d5\u05e6\u05e8\u05d9\u05d0\\\u05ea\u05dc\u05de\u05d5\u05d3\\\u05d1\u05d1\u05dc\u05d9\\\u05e1\u05d3\u05e8 \u05e7\u05d3\u05e9\u05d9\u05dd\\\u05d6\u05d1\u05d7\u05d9\u05dd","line_index_2":2067.0,"Conection Type":null},{"line_index_1":781.0,"heRef_2":"\u05d9\u05d5\u05de\u05d0 \u05e1:, \u05d6,","path_2":"\u05d0\u05d5\u05e6\u05e8\u05d9\u05d0\\\u05ea\u05dc\u05de\u05d5\u05d3\\\u05d1\u05d1\u05dc\u05d9\\\u05e1\u05d3\u05e8 \u05de\u05d5\u05e2\u05d3\\\u05d9\u05d5\u05de\u05d0","line_index_2":1575.0,"Conection Type":null},{"line_index_1":52.0,"heRef_2":"\u05d6\u05d1\u05d7\u05d9\u05dd \u05dc\u05d5:, \u05db,","path_2":"\u05d0\u05d5\u05e6\u05e8\u05d9\u05d0\\\u05ea\u05dc\u05de\u05d5\u05d3\\\u05d1\u05d1\u05dc\u05d9\\\u05e1\u05d3\u05e8 \u05e7\u05d3\u05e9\u05d9\u05dd\\\u05d6\u05d1\u05d7\u05d9\u05dd","line_index_2":1326.0,"Conection Type":null},{"line_index_1":60.0,"heRef_2":"\u05d6\u05d1\u05d7\u05d9\u05dd \u05dc\u05d8:, \u05d0,","path_2":"\u05d0\u05d5\u05e6\u05e8\u05d9\u05d0\\\u05ea\u05dc\u05de\u05d5\u05d3\\\u05d1\u05d1\u05dc\u05d9\\\u05e1\u05d3\u05e8 \u05e7\u05d3\u05e9\u05d9\u05dd\\\u05d6\u05d1\u05d7\u05d9\u05dd","line_index_2":1407.0,"Conection Type":null},{"line_index_1":850.0,"heRef_2":"\u05d9\u05d1\u05de\u05d5\u05ea \u05de\u05d8., \u05d0,","path_2":"\u05d0\u05d5\u05e6\u05e8\u05d9\u05d0\\\u05ea\u05dc\u05de\u05d5\u05d3\\\u05d1\u05d1\u05dc\u05d9\\\u05e1\u05d3\u05e8 \u05e0\u05e9\u05d9\u05dd\\\u05d9\u05d1\u05de\u05d5\u05ea","line_index_2":1637.0,"Conection Type":null},{"line_index_1":1031.0,"heRef_2":"\u05d6\u05d1\u05d7\u05d9\u05dd \u05e6\u05d7., \u05d9\u05d0,","path_2":"\u05d0\u05d5\u05e6\u05e8\u05d9\u05d0\\\u05ea\u05dc\u05de\u05d5\u05d3\\\u05d1\u05d1\u05dc\u05d9\\\u05e1\u05d3\u05e8 \u05e7\u05d3\u05e9\u05d9\u05dd\\\u05d6\u05d1\u05d7\u05d9\u05dd","line_index_2":3199.0,"Conection Type":null},{"line_index_1":1056.0,"heRef_2":"\u05d9\u05d1\u05de\u05d5\u05ea \u05e0\u05d4:, \u05d8,","path_2":"\u05d0\u05d5\u05e6\u05e8\u05d9\u05d0\\\u05ea\u05dc\u05de\u05d5\u05d3\\\u05d1\u05d1\u05dc\u05d9\\\u05e1\u05d3\u05e8 \u05e0\u05e9\u05d9\u05dd\\\u05d9\u05d1\u05de\u05d5\u05ea","line_index_2":1852.0,"Conection Type":null},{"line_index_1":1078.0,"heRef_2":"\u05d9\u05d1\u05de\u05d5\u05ea \u05e2\u05d7., \u05d9\u05d8,","path_2":"\u05d0\u05d5\u05e6\u05e8\u05d9\u05d0\\\u05ea\u05dc\u05de\u05d5\u05d3\\\u05d1\u05d1\u05dc\u05d9\\\u05e1\u05d3\u05e8 \u05e0\u05e9\u05d9\u05dd\\\u05d9\u05d1\u05de\u05d5\u05ea","line_index_2":2631.0,"Conection Type":null},{"line_index_1":104.0,"heRef_2":"\u05d6\u05db\u05e8\u05d9\u05d4 \u05d7, \u05d8\u05d6,","path_2":"\u05d0\u05d5\u05e6\u05e8\u05d9\u05d0\\\u05ea\u05e0\u05da\\\u05e0\u05d1\u05d9\u05d0\u05d9\u05dd\\\u05d6\u05db\u05e8\u05d9\u05d4","line_index_2":123.0,"Conection Type":null},{"line_index_1":1106.0,"heRef_2":"\u05d9\u05d1\u05de\u05d5\u05ea \u05de\u05d7:, \u05d8\u05d5,","path_2":"\u05d0\u05d5\u05e6\u05e8\u05d9\u05d0\\\u05ea\u05dc\u05de\u05d5\u05d3\\\u05d1\u05d1\u05dc\u05d9\\\u05e1\u05d3\u05e8 \u05e0\u05e9\u05d9\u05dd\\\u05d9\u05d1\u05de\u05d5\u05ea","line_index_2":1634.0,"Conection Type":null},{"line_index_1":1142.0,"heRef_2":"\u05d9\u05d1\u05de\u05d5\u05ea \u05e0\u05d8., \u05d9\u05d2,","path_2":"\u05d0\u05d5\u05e6\u05e8\u05d9\u05d0\\\u05ea\u05dc\u05de\u05d5\u05d3\\\u05d1\u05d1\u05dc\u05d9\\\u05e1\u05d3\u05e8 \u05e0\u05e9\u05d9\u05dd\\\u05d9\u05d1\u05de\u05d5\u05ea","line_index_2":1965.0,"Conection Type":null},{"line_index_1":1142.0,"heRef_2":"\u05d9\u05d1\u05de\u05d5\u05ea \u05e0\u05d4., \u05db\u05d3,","path_2":"\u05d0\u05d5\u05e6\u05e8\u05d9\u05d0\\\u05ea\u05dc\u05de\u05d5\u05d3\\\u05d1\u05d1\u05dc\u05d9\\\u05e1\u05d3\u05e8 \u05e0\u05e9\u05d9\u05dd\\\u05d9\u05d1\u05de\u05d5\u05ea","line_index_2":1840.0,"Conection Type":null},{"line_index_1":1156.0,"heRef_2":"\u05d9\u05d1\u05de\u05d5\u05ea \u05e6\u05d7., \u05d2,","path_2":"\u05d0\u05d5\u05e6\u05e8\u05d9\u05d0\\\u05ea\u05dc\u05de\u05d5\u05d3\\\u05d1\u05d1\u05dc\u05d9\\\u05e1\u05d3\u05e8 \u05e0\u05e9\u05d9\u05dd\\\u05d9\u05d1\u05de\u05d5\u05ea","line_index_2":3251.0,"Conection Type":null},{"line_index_1":1156.0,"heRef_2":"\u05d9\u05d1\u05de\u05d5\u05ea \u05e0\u05d2:, \u05d9\u05d1,","path_2":"\u05d0\u05d5\u05e6\u05e8\u05d9\u05d0\\\u05ea\u05dc\u05de\u05d5\u05d3\\\u05d1\u05d1\u05dc\u05d9\\\u05e1\u05d3\u05e8 \u05e0\u05e9\u05d9\u05dd\\\u05d9\u05d1\u05de\u05d5\u05ea","line_index_2":1767.0,"Conection Type":null},{"line_index_1":1156.0,"heRef_2":"\u05d9\u05d1\u05de\u05d5\u05ea \u05e7\u05d2., \u05d9\u05d6,","path_2":"\u05d0\u05d5\u05e6\u05e8\u05d9\u05d0\\\u05ea\u05dc\u05de\u05d5\u05d3\\\u05d1\u05d1\u05dc\u05d9\\\u05e1\u05d3\u05e8 \u05e0\u05e9\u05d9\u05dd\\\u05d9\u05d1\u05de\u05d5\u05ea","line_index_2":3435.0,"Conection Type":null},{"line_index_1":1184.0,"heRef_2":"\u05d9\u05d1\u05de\u05d5\u05ea \u05e7\u05d9\u05d1:, \u05d9\u05d8,","path_2":"\u05d0\u05d5\u05e6\u05e8\u05d9\u05d0\\\u05ea\u05dc\u05de\u05d5\u05d3\\\u05d1\u05d1\u05dc\u05d9\\\u05e1\u05d3\u05e8 \u05e0\u05e9\u05d9\u05dd\\\u05d9\u05d1\u05de\u05d5\u05ea","line_index_2":3778.0,"Conection Type":null},{"line_index_1":1234.0,"heRef_2":"\u05d6\u05d1\u05d7\u05d9\u05dd \u05e2:, \u05d8\u05d5,","path_2":"\u05d0\u05d5\u05e6\u05e8\u05d9\u05d0\\\u05ea\u05dc\u05de\u05d5\u05d3\\\u05d1\u05d1\u05dc\u05d9\\\u05e1\u05d3\u05e8 \u05e7\u05d3\u05e9\u05d9\u05dd\\\u05d6\u05d1\u05d7\u05d9\u05dd","line_index_2":2394.0,"Conection Type":null},{"line_index_1":1237.0,"heRef_2":"\u05d6\u05d1\u05d7\u05d9\u05dd \u05e2\u05d3., \u05d9\u05d2,","path_2":"\u05d0\u05d5\u05e6\u05e8\u05d9\u05d0\\\u05ea\u05dc\u05de\u05d5\u05d3\\\u05d1\u05d1\u05dc\u05d9\\\u05e1\u05d3\u05e8 \u05e7\u05d3\u05e9\u05d9\u05dd\\\u05d6\u05d1\u05d7\u05d9\u05dd","line_index_2":2456.0,"Conection Type":null},{"line_index_1":1242.0,"heRef_2":"\u05d9\u05d1\u05de\u05d5\u05ea \u05e2\u05d7., \u05d9\u05d8,","path_2":"\u05d0\u05d5\u05e6\u05e8\u05d9\u05d0\\\u05ea\u05dc\u05de\u05d5\u05d3\\\u05d1\u05d1\u05dc\u05d9\\\u05e1\u05d3\u05e8 \u05e0\u05e9\u05d9\u05dd\\\u05d9\u05d1\u05de\u05d5\u05ea","line_index_2":2631.0,"Conection Type":null},{"line_index_1":1258.0,"heRef_2":"\u05d9\u05d1\u05de\u05d5\u05ea \u05dc\u05d1:, \u05d0,","path_2":"\u05d0\u05d5\u05e6\u05e8\u05d9\u05d0\\\u05ea\u05dc\u05de\u05d5\u05d3\\\u05d1\u05d1\u05dc\u05d9\\\u05e1\u05d3\u05e8 \u05e0\u05e9\u05d9\u05dd\\\u05d9\u05d1\u05de\u05d5\u05ea","line_index_2":1002.0,"Conection Type":null},{"line_index_1":1261.0,"heRef_2":"\u05d9\u05d1\u05de\u05d5\u05ea \u05e1\u05d3:, \u05d8,","path_2":"\u05d0\u05d5\u05e6\u05e8\u05d9\u05d0\\\u05ea\u05dc\u05de\u05d5\u05d3\\\u05d1\u05d1\u05dc\u05d9\\\u05e1\u05d3\u05e8 \u05e0\u05e9\u05d9\u05dd\\\u05d9\u05d1\u05de\u05d5\u05ea","line_index_2":2144.0,"Conection Type":null},{"line_index_1":1267.0,"heRef_2":"\u05d9\u05d1\u05de\u05d5\u05ea \u05e1\u05d0., \u05d9\u05d1,","path_2":"\u05d0\u05d5\u05e6\u05e8\u05d9\u05d0\\\u05ea\u05dc\u05de\u05d5\u05d3\\\u05d1\u05d1\u05dc\u05d9\\\u05e1\u05d3\u05e8 \u05e0\u05e9\u05d9\u05dd\\\u05d9\u05d1\u05de\u05d5\u05ea","line_index_2":2029.0,"Conection Type":null},{"line_index_1":1270.0,"heRef_2":"\u05d6\u05d1\u05d7\u05d9\u05dd \u05e7\u05d6., \u05d9\u05d3,","path_2":"\u05d0\u05d5\u05e6\u05e8\u05d9\u05d0\\\u05ea\u05dc\u05de\u05d5\u05d3\\\u05d1\u05d1\u05dc\u05d9\\\u05e1\u05d3\u05e8 \u05e7\u05d3\u05e9\u05d9\u05dd\\\u05d6\u05d1\u05d7\u05d9\u05dd","line_index_2":3546.0,"Conection Type":null},{"line_index_1":1276.0,"heRef_2":"\u05d6\u05d1\u05d7\u05d9\u05dd \u05de\u05d4:, \u05d9\u05d6,","path_2":"\u05d0\u05d5\u05e6\u05e8\u05d9\u05d0\\\u05ea\u05dc\u05de\u05d5\u05d3\\\u05d1\u05d1\u05dc\u05d9\\\u05e1\u05d3\u05e8 \u05e7\u05d3\u05e9\u05d9\u05dd\\\u05d6\u05d1\u05d7\u05d9\u05dd","line_index_2":1595.0,"Conection Type":null},{"line_index_1":1279.0,"heRef_2":"\u05d6\u05d1\u05d7\u05d9\u05dd \u05e7\u05d5., \u05d8,","path_2":"\u05d0\u05d5\u05e6\u05e8\u05d9\u05d0\\\u05ea\u05dc\u05de\u05d5\u05d3\\\u05d1\u05d1\u05dc\u05d9\\\u05e1\u05d3\u05e8 \u05e7\u05d3\u05e9\u05d9\u05dd\\\u05d6\u05d1\u05d7\u05d9\u05dd","line_index_2":3503.0,"Conection Type":null},{"line_index_1":1295.0,"heRef_2":"\u05d6\u05d1\u05d7\u05d9\u05dd \u05de\u05d4:, \u05d3,","path_2":"\u05d0\u05d5\u05e6\u05e8\u05d9\u05d0\\\u05ea\u05dc\u05de\u05d5\u05d3\\\u05d1\u05d1\u05dc\u05d9\\\u05e1\u05d3\u05e8 \u05e7\u05d3\u05e9\u05d9\u05dd\\\u05d6\u05d1\u05d7\u05d9\u05dd","line_index_2":1582.0,"Conection Type":null},{"line_index_1":1331.0,"heRef_2":"\u05d9\u05d1\u05de\u05d5\u05ea \u05e2\u05d3:, \u05d9\u05d6,","path_2":"\u05d0\u05d5\u05e6\u05e8\u05d9\u05d0\\\u05ea\u05dc\u05de\u05d5\u05d3\\\u05d1\u05d1\u05dc\u05d9\\\u05e1\u05d3\u05e8 \u05e0\u05e9\u05d9\u05dd\\\u05d9\u05d1\u05de\u05d5\u05ea","line_index_2":2497.0,"Conection Type":null},{"line_index_1":1349.0,"heRef_2":"\u05d6\u05d1\u05d7\u05d9\u05dd \u05e0\u05d3:, \u05d5,","path_2":"\u05d0\u05d5\u05e6\u05e8\u05d9\u05d0\\\u05ea\u05dc\u05de\u05d5\u05d3\\\u05d1\u05d1\u05dc\u05d9\\\u05e1\u05d3\u05e8 \u05e7\u05d3\u05e9\u05d9\u05dd\\\u05d6\u05d1\u05d7\u05d9\u05dd","line_index_2":1887.0,"Conection Type":null},{"line_index_1":1364.0,"heRef_2":"\u05d9\u05d1\u05de\u05d5\u05ea \u05e7\u05d9:, \u05d9\u05d1,","path_2":"\u05d0\u05d5\u05e6\u05e8\u05d9\u05d0\\\u05ea\u05dc\u05de\u05d5\u05d3\\\u05d1\u05d1\u05dc\u05d9\\\u05e1\u05d3\u05e8 \u05e0\u05e9\u05d9\u05dd\\\u05d9\u05d1\u05de\u05d5\u05ea","line_index_2":3700.0,"Conection Type":null},{"line_index_1":1386.0,"heRef_2":"\u05d9\u05d1\u05de\u05d5\u05ea \u05e6:, \u05d4,","path_2":"\u05d0\u05d5\u05e6\u05e8\u05d9\u05d0\\\u05ea\u05dc\u05de\u05d5\u05d3\\\u05d1\u05d1\u05dc\u05d9\\\u05e1\u05d3\u05e8 \u05e0\u05e9\u05d9\u05dd\\\u05d9\u05d1\u05de\u05d5\u05ea","line_index_2":3007.0,"Conection Type":null}]